VolumetricSMPL/__init__.py
VolumetricSMPL/modules.py
VolumetricSMPL/volumetric_smpl.py
VolumetricSMPL/winding_numbers.py
VolumetricSMPL-1.0.3.dist-info/LICENSE
VolumetricSMPL-1.0.3.dist-info/METADATA
VolumetricSMPL-1.0.3.dist-info/WHEEL
VolumetricSMPL-1.0.3.dist-info/top_level.txt
VolumetricSMPL-1.0.3.dist-info/RECORD
