Metadata-Version: 2.2
Name: VolumetricSMPL
Version: 1.0.3
Summary: VolumetricSMPL body model.
Home-page: https://github.com/markomih/VolumetricSMPL
Author: Marko Mihajlovic
Author-email: markomih@inf.ethz.ch
License: MIT
Requires-Python: >=3.6.0
License-File: LICENSE
Requires-Dist: numpy>=1.12.2
Requires-Dist: trimesh
Requires-Dist: scikit-image
Requires-Dist: smplx
Dynamic: author
Dynamic: author-email
Dynamic: description
Dynamic: description-content-type
Dynamic: home-page
Dynamic: license
Dynamic: requires-dist
Dynamic: requires-python
Dynamic: summary
